{
"type": "FeatureCollection",
"name": "TourW_2",
"crs": { "type": "name", "properties": { "name": "urn:ogc:def:crs:OGC:1.3:CRS84" } },
"features": [
{ "type": "Feature", "properties": { "Nom": "Tour W, 102, Terrasse Boieldieu, La Défense 8, Puteaux, Arrondissement of Nanterre, Hauts-de-Seine, Ile-de-France, Metropolitan France, 92800, France" }, "geometry": { "type": "Point", "coordinates": [ 2.238896940931512, 48.889231 ] } }
]
}
